bc_dock_util/__init__.py
bc_dock_util/bc_dock_util.py
bc_dock_util-0.1.0.dist-info/LICENSE
bc_dock_util-0.1.0.dist-info/METADATA
bc_dock_util-0.1.0.dist-info/WHEEL
bc_dock_util-0.1.0.dist-info/top_level.txt
bc_dock_util-0.1.0.dist-info/RECORD
