Metadata-Version: 2.1
Name: bc-dock-util
Version: 0.1.0
Summary: B client docking tianxiaxinyong service sdk util.
Home-page: https://github.com/pytxxy/bc_dock_util
Author: caifh
Author-email: caifh@tianxiaxinyong.com
License: UNKNOWN
Platform: UNKNOWN
Classifier: Programming Language :: Python :: 2.7
Classifier: Programming Language :: Python :: 3
Classifier: License :: OSI Approved :: MIT License
Classifier: Operating System :: OS Independent
Requires-Dist: pycryptodome (>=3.5.1)
Requires-Dist: cryptography (>=2.3)
Requires-Dist: Requests (>=2.19.1)
